odoo/addons/l10n_ro_account_edit_currency_rate/README.rst
odoo/addons/l10n_ro_account_edit_currency_rate/__init__.py
odoo/addons/l10n_ro_account_edit_currency_rate/__manifest__.py
odoo/addons/l10n_ro_account_edit_currency_rate/i18n/l10n_ro_account_edit_currency_rate.pot
odoo/addons/l10n_ro_account_edit_currency_rate/i18n/ro.po
odoo/addons/l10n_ro_account_edit_currency_rate/readme/CONTRIBUTORS.md
odoo/addons/l10n_ro_account_edit_currency_rate/readme/DESCRIPTION.md
odoo/addons/l10n_ro_account_edit_currency_rate/readme/INSTALL.md
odoo/addons/l10n_ro_account_edit_currency_rate/static/description/icon.png
odoo/addons/l10n_ro_account_edit_currency_rate/static/description/index.html
odoo/addons/l10n_ro_account_edit_currency_rate/views/account_invoice_view.xml
odoo_addon_l10n_ro_account_edit_currency_rate-18.0.0.2.0.dist-info/METADATA
odoo_addon_l10n_ro_account_edit_currency_rate-18.0.0.2.0.dist-info/WHEEL
odoo_addon_l10n_ro_account_edit_currency_rate-18.0.0.2.0.dist-info/top_level.txt
odoo_addon_l10n_ro_account_edit_currency_rate-18.0.0.2.0.dist-info/RECORD
