Metadata-Version: 2.1
Name: odoo-addon-l10n_ro_account_edit_currency_rate
Version: 18.0.0.2.0
Requires-Python: >=3.10
Requires-Dist: odoo==18.0.*
Summary: Romania - Invoice Edit Currency Rate
Home-page: https://github.com/OCA/l10n-romania
License: AGPL-3
Author: NextERP Romania,Odoo Community Association (OCA)
Author-email: support@odoo-community.org
Classifier: Programming Language :: Python
Classifier: Framework :: Odoo
Classifier: Framework :: Odoo :: 18.0
Classifier: License :: OSI Approved :: GNU Affero General Public License v3
Classifier: Development Status :: 6 - Mature
